stand013/__init__.py
stand013/_enums.py
stand013/cli.py
stand013/schemas/STAND013 Faktura v1.0 (XML).xsd
stand013/schemas/STAND013 Fakturakvittering 1.0 (XML).xsd
stand013/schemas/STAND013-Components_v1p1.xsd
stand013/schemas/STAND013-DeliveryNote_Interchange_v1p1.xsd
stand013/schemas/STAND013-DeliveryNote_v1p1.xsd
stand013/schemas/STAND013-OrderResponse-Receipt_v1p1.xsd
stand013/schemas/STAND013-OrderResponse_Interchange_v1p1.xsd
stand013/schemas/STAND013-OrderResponse_Receipt-Interchange_v1p1.xsd
stand013/schemas/STAND013-OrderResponse_v1p1.xsd
stand013/schemas/STAND013-Order_Interchange_v1p1.xsd
stand013/schemas/STAND013-Order_v1p1.xsd
stand013/validation.py
stand013-0.1.0.dist-info/entry_points.txt
stand013-0.1.0.dist-info/LICENSE
stand013-0.1.0.dist-info/WHEEL
stand013-0.1.0.dist-info/METADATA
stand013-0.1.0.dist-info/RECORD
