Metadata-Version: 2.1
Name: stand013
Version: 0.1.0
Summary: STAND13 file format parsing, writing, and validation.
Home-page: https://github.com/kolonialno/python-stand013
License: MIT
Author: Stein Magnus Jodal
Author-email: stein.magnus.jodal@oda.com
Requires-Python: >=3.7,<4.0
Classifier: Development Status :: 3 - Alpha
Classifier: Intended Audience :: Developers
Classifier: License :: OSI Approved :: MIT License
Classifier: Programming Language :: Python :: 3
Classifier: Programming Language :: Python :: 3.7
Classifier: Programming Language :: Python :: 3.8
Classifier: Programming Language :: Python :: 3.9
Classifier: Topic :: Software Development :: Libraries
Requires-Dist: importlib_metadata (>=1.6,<5.0); python_version < "3.8"
Requires-Dist: lxml (>=4.6.3,<5.0.0)
Requires-Dist: typer (>=0.3.2,<0.4.0)
Requires-Dist: xmlschema (>=1.6.4,<2.0.0)
Project-URL: Repository, https://github.com/kolonialno/python-stand013
